robotframework_browser_recorder/__init__.py
robotframework_browser_recorder/recorder.py
robotframework_browser_recorder/cli/__init__.py
robotframework_browser_recorder/cli/main.py
robotframework_browser_recorder/converter/__init__.py
robotframework_browser_recorder/converter/playwright_to_robot.py
robotframework_browser_recorder/utils/__init__.py
robotframework_browser_recorder-0.3.0.dist-info/licenses/LICENSE
robotframework_browser_recorder-0.3.0.dist-info/METADATA
robotframework_browser_recorder-0.3.0.dist-info/WHEEL
robotframework_browser_recorder-0.3.0.dist-info/entry_points.txt
robotframework_browser_recorder-0.3.0.dist-info/top_level.txt
robotframework_browser_recorder-0.3.0.dist-info/RECORD
