Metadata-Version: 2.4
Name: robotframework-browser-recorder
Version: 0.3.0
Summary: Record browser interactions and generate Robot Framework tests using Browser library
Author: Robot Framework Browser Recorder Contributors
License: Apache-2.0
Project-URL: Homepage, https://github.com/yourusername/robotframework-browser-recorder
Project-URL: Documentation, https://github.com/yourusername/robotframework-browser-recorder#readme
Project-URL: Repository, https://github.com/yourusername/robotframework-browser-recorder
Project-URL: Issues, https://github.com/yourusername/robotframework-browser-recorder/issues
Keywords: robotframework,browser,playwright,testing,automation,recorder
Classifier: Development Status :: 4 - Beta
Classifier: Intended Audience :: Developers
Classifier: License :: OSI Approved :: Apache Software License
Classifier: Programming Language :: Python :: 3
Classifier: Programming Language :: Python :: 3.8
Classifier: Programming Language :: Python :: 3.9
Classifier: Programming Language :: Python :: 3.10
Classifier: Programming Language :: Python :: 3.11
Classifier: Programming Language :: Python :: 3.12
Classifier: Topic :: Software Development :: Testing
Classifier: Framework :: Robot Framework
Requires-Python: >=3.8
License-File: LICENSE
Requires-Dist: playwright>=1.40.0
Requires-Dist: robotframework>=6.0
Requires-Dist: robotframework-browser>=17.0.0
Provides-Extra: dev
Requires-Dist: pytest>=7.0; extra == "dev"
Requires-Dist: pytest-cov>=4.0; extra == "dev"
Requires-Dist: black>=23.0; extra == "dev"
Requires-Dist: flake8>=6.0; extra == "dev"
Requires-Dist: mypy>=1.0; extra == "dev"
Dynamic: license-file
